COPYING
README.md
pyproject.toml
setup.py
frida_tools/__init__.py
frida_tools/_repl_magic.py
frida_tools/apk.py
frida_tools/application.py
frida_tools/cli_formatting.py
frida_tools/compiler.py
frida_tools/creator.py
frida_tools/discoverer.py
frida_tools/fs_agent.js
frida_tools/itracer.py
frida_tools/itracer_agent.js
frida_tools/join.py
frida_tools/kill.py
frida_tools/ls.py
frida_tools/lsd.py
frida_tools/model.py
frida_tools/pm.py
frida_tools/ps.py
frida_tools/pull.py
frida_tools/push.py
frida_tools/reactor.py
frida_tools/repl.py
frida_tools/repl_agent.js
frida_tools/rm.py
frida_tools/stream_controller.py
frida_tools/tracer.py
frida_tools/tracer_agent.js
frida_tools/tracer_ui.zip
frida_tools/units.py
frida_tools.egg-info/PKG-INFO
frida_tools.egg-info/SOURCES.txt
frida_tools.egg-info/dependency_links.txt
frida_tools.egg-info/entry_points.txt
frida_tools.egg-info/not-zip-safe
frida_tools.egg-info/requires.txt
frida_tools.egg-info/top_level.txt
frida_tools/bridges/java.js
frida_tools/bridges/objc.js
frida_tools/bridges/swift.js
tests/test_arguments.py
tests/test_discoverer.py
tests/test_tracer.py